magma/__init__.py
magma/array.py
magma/ast_utils.py
magma/bit.py
magma/bit_vector.py
magma/bits.py
magma/bitutils.py
magma/braid.py
magma/circuit.py
magma/circuit_def.py
magma/clock.py
magma/compatibility.py
magma/compile.py
magma/config.py
magma/conversions.py
magma/debug.py
magma/enum.py
magma/fromverilog.py
magma/interface.py
magma/ir.py
magma/is_definition.py
magma/is_primitive.py
magma/logging.py
magma/operators.py
magma/port.py
magma/product.py
magma/ref.py
magma/scope.py
magma/t.py
magma/transforms.py
magma/tuple.py
magma/uniquification.py
magma/util.py
magma/waveform.py
magma/wire.py
magma/backend/__init__.py
magma/backend/blif.py
magma/backend/coreir_.py
magma/backend/dot.py
magma/backend/firrtl.py
magma/backend/util.py
magma/backend/verilog.py
magma/frontend/__init__.py
magma/frontend/coreir.py
magma/frontend/coreir_.py
magma/passes/__init__.py
magma/passes/clock.py
magma/passes/debug_name.py
magma/passes/ir.py
magma/passes/passes.py
magma/passes/tsort.py
magma/simulator/__init__.py
magma/simulator/coreir_simulator.py
magma/simulator/mdb.py
magma/simulator/python_simulator.py
magma/simulator/simulator.py
magma/ssa/__init__.py
magma/ssa/ssa.py
magma/syntax/__init__.py
magma/syntax/combinational.py
magma/syntax/sequential.py
magma/syntax/util.py
magma/testing/__init__.py
magma/testing/compile.py
magma/testing/coroutine.py
magma/testing/utils.py
magma_lang-1.0.2.data/scripts/magma
magma_lang-1.0.2.dist-info/LICENSE.txt
magma_lang-1.0.2.dist-info/METADATA
magma_lang-1.0.2.dist-info/WHEEL
magma_lang-1.0.2.dist-info/top_level.txt
magma_lang-1.0.2.dist-info/RECORD
