Metadata-Version: 2.1
Name: magma-lang
Version: 1.0.2
Summary: An embedded DSL for constructing hardware circuits
Home-page: https://github.com/phanrahan/magma
Maintainer: Lenny Truong
Maintainer-email: lenny@cs.stanford.edu
License: MIT
Platform: UNKNOWN
Requires-Python: >=3.6
Requires-Dist: colorlog
Requires-Dist: astor
Requires-Dist: six
Requires-Dist: mako
Requires-Dist: pyverilog
Requires-Dist: numpy
Requires-Dist: graphviz
Requires-Dist: coreir (>=1.0.*)
Requires-Dist: hwtypes (>=1.0.*)
